nccommon/__init__.py
nccommon/helloworld.py
nccommon-0.0.3.dist-info/LICENSE
nccommon-0.0.3.dist-info/METADATA
nccommon-0.0.3.dist-info/WHEEL
nccommon-0.0.3.dist-info/top_level.txt
nccommon-0.0.3.dist-info/RECORD
