Metadata-Version: 2.1
Name: nccommon
Version: 0.0.3
Summary: A simple package to print Hello, World! by abhishek
Home-page: https://github.com/abhishek.maurya/Abhishekkapackage
Author: Abhishek Maurya
Author-email: abhishek.mauryanetcore@gmail.com
License: UNKNOWN
Platform: UNKNOWN
Classifier: Programming Language :: Python :: 3
Classifier: License :: OSI Approved :: MIT License
Classifier: Operating System :: OS Independent
Requires-Python: >=3.6
License-File: LICENSE
